simpletasks/__init__.py
simpletasks/cli.py
simpletasks/helpers.py
simpletasks/orchestrator.py
simpletasks/pipeline.py
simpletasks/task.py
simpletasks-0.1.2.dist-info/LICENSE
simpletasks-0.1.2.dist-info/WHEEL
simpletasks-0.1.2.dist-info/METADATA
simpletasks-0.1.2.dist-info/RECORD
